fairlib/__init__.py
fairlib/__main__.py
fairlib/datasets/__init__.py
fairlib/datasets/Adult/Adult.py
fairlib/datasets/Adult/__init__.py
fairlib/datasets/COMPAS/COMPAS.py
fairlib/datasets/COMPAS/__init__.py
fairlib/datasets/MSCOCO/__init__.py
fairlib/datasets/MSCOCO/coco.py
fairlib/datasets/TP_POS/__init__.py
fairlib/datasets/TP_POS/pos.py
fairlib/datasets/bios/__init__.py
fairlib/datasets/bios/bios.py
fairlib/datasets/coloredMNIST/MNIST.py
fairlib/datasets/coloredMNIST/__init__.py
fairlib/datasets/imSitu/__init__.py
fairlib/datasets/imSitu/imSitu.py
fairlib/datasets/moji/__init__.py
fairlib/datasets/moji/moji.py
fairlib/datasets/moji/processed.py
fairlib/datasets/utils/__init__.py
fairlib/datasets/utils/bert_encoding.py
fairlib/datasets/utils/download.py
fairlib/datasets/utils/preprocessing.py
fairlib/datasets/utils/unzip.py
fairlib/src/__init__.py
fairlib/src/base_options.py
fairlib/src/analysis/__init__.py
fairlib/src/analysis/load_results.py
fairlib/src/analysis/tables_and_figures.py
fairlib/src/analysis/utils.py
fairlib/src/dataloaders/BT.py
fairlib/src/dataloaders/__init__.py
fairlib/src/dataloaders/encoder.py
fairlib/src/dataloaders/generalized_BT.py
fairlib/src/dataloaders/utils.py
fairlib/src/dataloaders/loaders/Adult.py
fairlib/src/dataloaders/loaders/Bios.py
fairlib/src/dataloaders/loaders/COMPAS.py
fairlib/src/dataloaders/loaders/ColoredMNIST.py
fairlib/src/dataloaders/loaders/FCL_BiosDataset.py
fairlib/src/dataloaders/loaders/Moji.py
fairlib/src/dataloaders/loaders/Trustpilot.py
fairlib/src/dataloaders/loaders/Valence.py
fairlib/src/dataloaders/loaders/__init__.py
fairlib/src/dataloaders/loaders/imSitu.py
fairlib/src/dataloaders/loaders/loaders.py
fairlib/src/evaluators/__init__.py
fairlib/src/evaluators/double_corrected_variance_estimator.py
fairlib/src/evaluators/evaluator.py
fairlib/src/evaluators/gerrymandering_groups.py
fairlib/src/evaluators/leakage_metrices.py
fairlib/src/evaluators/utils.py
fairlib/src/networks/__init__.py
fairlib-0.1.0.dist-info/LICENSE
fairlib-0.1.0.dist-info/METADATA
fairlib-0.1.0.dist-info/WHEEL
fairlib-0.1.0.dist-info/top_level.txt
fairlib-0.1.0.dist-info/RECORD
