Metadata-Version: 2.1
Name: fairlib
Version: 0.1.0
Summary: Unified framework for assessing and improving fairness.
Home-page: https://github.com/HanXudong/fairlib
Author: Xudong Han
Author-email: xudongh1@student.unimelb.edu.au
Classifier: Programming Language :: Python :: 3
Classifier: License :: OSI Approved :: Apache Software License
Classifier: Topic :: Scientific/Engineering :: Artificial Intelligence
Classifier: Natural Language :: English
Requires-Python: >=3.7
License-File: LICENSE
Requires-Dist: tqdm
Requires-Dist: numpy
Requires-Dist: docopt
Requires-Dist: pandas
Requires-Dist: scikit-learn
Requires-Dist: torch
Requires-Dist: PyYAML
Requires-Dist: seaborn
Requires-Dist: matplotlib
Requires-Dist: pickle5
Requires-Dist: transformers
Requires-Dist: sacremoses
Requires-Dist: sentencepiece
